{
  "totalContributions": 847,
  "weeks": [
    {"contributionDays": [{"contributionCount": 2, "date": "2024-03-01", "weekday": 5}, {"contributionCount": 0, "date": "2024-03-02", "weekday": 6}, {"contributionCount": 5, "date": "2024-03-03", "weekday": 0}, {"contributionCount": 8, "date": "2024-03-04", "weekday": 1}, {"contributionCount": 3, "date": "2024-03-05", "weekday": 2}, {"contributionCount": 12, "date": "2024-03-06", "weekday": 3}, {"contributionCount": 7, "date": "2024-03-07", "weekday": 4}]},
    {"contributionDays": [{"contributionCount": 4, "date": "2024-03-08", "weekday": 5}, {"contributionCount": 0, "date": "2024-03-09", "weekday": 6}, {"contributionCount": 6, "date": "2024-03-10", "weekday": 0}, {"contributionCount": 9, "date": "2024-03-11", "weekday": 1}, {"contributionCount": 15, "date": "2024-03-12", "weekday": 2}, {"contributionCount": 3, "date": "2024-03-13", "weekday": 3}, {"contributionCount": 8, "date": "2024-03-14", "weekday": 4}]},
    {"contributionDays": [{"contributionCount": 2, "date": "2024-03-15", "weekday": 5}, {"contributionCount": 1, "date": "2024-03-16", "weekday": 6}, {"contributionCount": 7, "date": "2024-03-17", "weekday": 0}, {"contributionCount": 11, "date": "2024-03-18", "weekday": 1}, {"contributionCount": 4, "date": "2024-03-19", "weekday": 2}, {"contributionCount": 9, "date": "2024-03-20", "weekday": 3}, {"contributionCount": 6, "date": "2024-03-21", "weekday": 4}]},
    {"contributionDays": [{"contributionCount": 3, "date": "2024-03-22", "weekday": 5}, {"contributionCount": 0, "date": "2024-03-23", "weekday": 6}, {"contributionCount": 8, "date": "2024-03-24", "weekday": 0}, {"contributionCount": 14, "date": "2024-03-25", "weekday": 1}, {"contributionCount": 5, "date": "2024-03-26", "weekday": 2}, {"contributionCount": 10, "date": "2024-03-27", "weekday": 3}, {"contributionCount": 7, "date": "2024-03-28", "weekday": 4}]},
    {"contributionDays": [{"contributionCount": 2, "date": "2024-03-29", "weekday": 5}, {"contributionCount": 0, "date": "2024-03-30", "weekday": 6}, {"contributionCount": 6, "date": "2024-03-31", "weekday": 0}, {"contributionCount": 9, "date": "2024-04-01", "weekday": 1}, {"contributionCount": 13, "date": "2024-04-02", "weekday": 2}, {"contributionCount": 4, "date": "2024-04-03", "weekday": 3}, {"contributionCount": 11, "date": "2024-04-04", "weekday": 4}]},
    {"contributionDays": [{"contributionCount": 1, "date": "2024-04-05", "weekday": 5}, {"contributionCount": 0, "date": "2024-04-06", "weekday": 6}, {"contributionCount": 5, "date": "2024-04-07", "weekday": 0}, {"contributionCount": 8, "date": "2024-04-08", "weekday": 1}, {"contributionCount": 12, "date": "2024-04-09", "weekday": 2}, {"contributionCount": 6, "date": "2024-04-10", "weekday": 3}, {"contributionCount": 9, "date": "2024-04-11", "weekday": 4}]}
  ]
}
